{"nodes": [{"id": "DSC_0436_photographer_sea_lion", "label": "Photographer with Galapagos Sea Lion Pup on White Sand Beach", "file_type": "image", "source_file": "frontend/public/images/hero-main/computer/DSC_0436.webp", "source_location": null, "source_url": null, "captured_at": null, "author": null, "contributor": null}], "edges": [{"source": "DSC_0436_photographer_sea_lion", "target": "region_galapagos", "relation": "conceptually_related_to", "confidence": "EXTRACTED", "confidence_score": 1.0, "source_file": "frontend/public/images/hero-main/computer/DSC_0436.webp", "source_location": null, "weight": 1.0}, {"source": "DSC_0436_photographer_sea_lion", "target": "concept_hero_images_manifest", "relation": "conceptually_related_to", "confidence": "EXTRACTED", "confidence_score": 1.0, "source_file": "frontend/public/images/hero-main/computer/DSC_0436.webp", "source_location": null, "weight": 1.0}, {"source": "DSC_0436_photographer_sea_lion", "target": "GLP_children_sealions_sandcastles", "relation": "semantically_similar_to", "confidence": "INFERRED", "confidence_score": 0.85, "source_file": "frontend/public/images/hero-main/computer/DSC_0436.webp", "source_location": null, "weight": 0.85}, {"source": "DSC_0436_photographer_sea_lion", "target": "movile_lobito_sea_lion_pup", "relation": "semantically_similar_to", "confidence": "INFERRED", "confidence_score": 0.85, "source_file": "frontend/public/images/hero-main/computer/DSC_0436.webp", "source_location": null, "weight": 0.85}], "hyperedges": []}